cubicweb_mock_schema/__init__.py
cubicweb_mock_schema/__pkginfo__.py
cubicweb_mock_schema/attribute.py
cubicweb_mock_schema/blog.py
cubicweb_mock_schema/relation.py
cubicweb_mock_schema-0.3.0.dist-info/METADATA
cubicweb_mock_schema-0.3.0.dist-info/WHEEL
cubicweb_mock_schema-0.3.0.dist-info/top_level.txt
cubicweb_mock_schema-0.3.0.dist-info/RECORD
