Metadata-Version: 2.1
Name: cubicweb-mock-schema
Version: 0.3.0
Summary: a repository of schemas for testing
Home-page: https://forge.extranet.logilab.fr/cubicweb/cubicweb-mock-schema/
Author: Logilab
Author-email: contact@logilab.fr
License: LGPL
Classifier: Framework :: CubicWeb
Classifier: Programming Language :: Python
Classifier: Programming Language :: Python :: 3
Classifier: Programming Language :: Python :: 3 :: Only
Requires-Dist: yams >=1.0.0
Requires-Dist: pytz >=2023.3
